Workbook

Sheet Master Data
A1: Employee ID | B1: Name | C1: Department | D1: Position | E1: Entry Date | F1: FTE | G1: Cost Center | H1: Status
A2: 144 | C2: Счетоводство | D2: Старши счетоводител | E2: 40361 | F2: 1 | G2: 5400 | H2: Active
A3: 66 | C3: Заваръчно | D3: Заварчик | E3: 41387 | F3: 1 | G3: 1400 | H3: Active | J3: Row Labels | K3: Count of Name
A4: 748 | C4: Преси | D4: Оператор, преса за метал | E4: 46034 | F4: 1 | G4: 1200 | H4: Inactive | J4: Автоматизация | K4: 6
A5: 753 | C5: Монтаж | D5: Машинен оператор | E5: 46062 | F5: 1 | G5: 1600 | H5: Active | J5: Дизайн на автоматизация | K5: 2
A6: 747 | C6: Монтаж | D6: Монтажник, изделия от метал | E6: 46029 | F6: 1 | G6: 1600 | H6: Active | J6: Дизайн на инструменти | K6: 2
A7: 648 | C7: Механична обработка | D7: Машинен оператор, металообработващи машини | E7: 44845 | F7: 1 | G7: 1300 | H7: Active | J7: Заваръчно | K7: 5
A8: 263 | C8: Калкулация | D8: Технолог | E8: 41821 | F8: 1 | G8: 4400 | H8: Active | J8: Заготовки за производство | K8: 2
A9: 719 | C9: ТРАНСПОРТ | D9: Шофьор, лекотоварен автомобил | E9: 45670 | F9: 1 | G9: 3900 | H9: Active | J9: Инструментален отдел | K9: 11
A10: 67 | C10: Механична обработка | D10: Настройчик, металообработващи машини с цифрово управление | E10: 41334 | F10: 1 | G10: 1300 | H10: Active | J10: Калкулация | K10: 2
A11: 615 | C11: Преси | D11: Машинен оператор, металообработващи машини | E11: 44634 | F11: 1 | G11: 1200 | H11: Active | J11: Механична обработка | K11: 23
A12: 465 | C12: Инструментален отдел | D12: Матричар | E12: 43412 | F12: 1 | G12: 2100 | H12: Active | J12: Монтаж | K12: 46
A13: 608 | C13: Монтаж | D13: Монтажник, изделия от метал | E13: 44593 | F13: 1 | G13: 1600 | H13: Active | J13: Общи IT | K13: 2
A14: 55 | C14: Преси | D14: Оператор, преса за метал | E14: 41535 | F14: 1 | G14: 1200 | H14: Active | J14: Осигуряване на качеството | K14: 5
A15: 6 | C15: Монтаж | D15: Монтажник, изделия от метал | E15: 38687 | F15: 1 | G15: 1600 | H15: Active | J15: Поддръжка машини | K15: 2
... A30: 726 | C30: Монтаж | D30: Машинен оператор | E30: 45804 | F30: 1 | G30: 1600 | H30: Active | J30: Grand Total | K30: 154
A31: 231 | C31: Развойна дейност | D31: Инженер, конструктор | E31: 41535 | F31: 1 | G31: 4500 | H31: Active
A32: 610 | C32: Механична обработка | D32: Настройчик, металообработващи машини с цифрово управление | E32: 44628 | F32: 1 | G32: 1300 | H32: Active
A33: 751 | C33: Механична обработка | D33: Настройчик, металообработващи машини с цифрово управление | E33: 46055 | F33: 1 | G33: 1300 | H33: Active
A34: 623 | C34: Инструментален отдел | D34: Машинен оператор, металообработващи машини | E34: 44691 | F34: 1 | G34: 2100 | H34: Active
A35: 745 | C35: Механична обработка | D35: Настройчик, металообработващи машини | E35: 45992 | F35: 1 | G35: 1300 | H35: Active
A36: 756 | C36: Монтаж | D36: Монтажник, изделия от метал | E36: 46076 | F36: 1 | G36: 1600 | H36: Active
A37: 404 | C37: Монтаж | D37: Монтажник, изделия от метал | E37: 42772 | F37: 1 | G37: 1600 | H37: Active
A38: 277 | C38: Преси | D38: Настройчик, пресови металообработващи машини | E38: 41885 | F38: 1 | G38: 1200 | H38: Active
A39: 644 | C39: Осигуряване на качеството | D39: Инженер, качество | E39: 44838 | F39: 1 | G39: 3500 | H39: Active
A40: 472 | C40: Инструментален отдел | D40: Машинен оператор, металообработващи машини | E40: 43479 | F40: 1 | G40: 2100 | H40: Active
A41: 542 | C41: Механична обработка | D41: Машинен оператор, металообработващи машини | E41: 43896 | F41: 1 | G41: 1300 | H41: Active
A42: 494 | C42: Осигуряване на качеството | D42: Окачествител, продукти (без храни и напитки) | E42: 43647 | F42: 1 | G42: 3500 | H42: Active
... A155: 12 | C155: Общи IT | D155: Администратор, информационни системи | E155: 38852 | F155: 1 | G155: 5600 | H155: Active

Sheet Salary History
A1: Employee ID | B1: Effective Date | C1: Name | D1: Cost Center | E1: Department | F1: Base Salary (Gross) | G1: Professional experience (Gross) | H1: Fixed Bonus (Gross) | I1: Food Vaucher | J1: Total (Gross) | K1: Salary (netto) | L1: Total Monthly Salary (netto) include food vaucher | M1: Annual Salary (netto) | N1: Month Employer Cost | O1: Annual Employer Cost | P1: % Increase | Q1: Reason | R1: Approved By | S1: Approval Date | T1: Comment | V1: Years (Effective Date) | W1: 2026
A2: 144 | B2: 46023 | D2: =VLOOKUP(C2,'Master Data'!$B$2:$G$155,6,0) -> #N/A | E2: Счетоводство | F2: 1431.62 | G2: 206.15328 | H2: 357.9 | I2: 102.26 | J2: =F2+G2+H2 -> 1995.6733 | K2: 1548.6425 | L2: =K2+I2 -> 1650.9025 | M2: =L2*12 -> 19810.83 | N2: =J2+(19.62%*(J2)+I2) -> 2489.4844 | O2: =N2*12 -> 29873.813 | V2: Months (Effective Date) | W2: (All)
A3: 66 | B3: 46023 | D3: =VLOOKUP(C3,'Master Data'!$B$2:$G$155,6,0) -> #N/A | E3: Заваръчно | F3: 639.12 | G3: 46.01664 | H3: 546.57 | I3: 102.26 | J3: =F3+G3+H3 -> 1231.7066 | K3: 955.80435 | L3: =K3+I3 -> 1058.0644 | M3: =L3*12 -> 12696.772 | N3: =J3+(19.62%*(J3)+I3) -> 1575.6275 | O3: =N3*12 -> 18907.53 | V3: Effective Date | W3: (All)
A4: 748 | B4: 46023 | D4: =VLOOKUP(C4,'Master Data'!$B$2:$G$155,6,0) -> #N/A | E4: Преси | F4: 675.01 | G4: 0 | H4: 412.2 | I4: 102.26 | J4: =F4+G4+H4 -> 1087.21 | K4: 843.67496 | L4: =K4+I4 -> 945.93496 | M4: =L4*12 -> 11351.22 | N4: =J4+(19.62%*(J4)+I4) -> 1402.7806 | O4: =N4*12 -> 16833.367 | V4: Quarters (Effective Date) | W4: (All)
A5: 753 | B5: 46023 | D5: =VLOOKUP(C5,'Master Data'!$B$2:$G$155,6,0) -> #N/A | E5: Монтаж | F5: 737 | G5: 0 | H5: 123.84 | I5: 102.26 | J5: =F5+G5+H5 -> 860.84 | K5: 668.01184 | L5: =K5+I5 -> 770.27184 | M5: =L5*12 -> 9243.2621 | N5: =J5+(19.62%*(J5)+I5) -> 1131.9968 | O5: =N5*12 -> 13583.962
A6: 747 | B6: 46023 | D6: =VLOOKUP(C6,'Master Data'!$B$2:$G$155,6,0) -> #N/A | E6: Монтаж | F6: 639.12 | G6: 0 | H6: 85.67 | I6: 102.26 | J6: =F6+G6+H6 -> 724.79 | K6: 562.43704 | L6: =K6+I6 -> 664.69704 | M6: =L6*12 -> 7976.3645 | N6: =J6+(19.62%*(J6)+I6) -> 969.2538 | O6: =N6*12 -> 11631.046 | V6: Row Labels | W6: Sum of Month Employer Cost | X6: Sum of Annual Employer Cost | Y6: Sum of Annual Salary (netto)
A7: 648 | B7: 46023 | D7: =VLOOKUP(C7,'Master Data'!$B$2:$G$155,6,0) -> #N/A | E7: Механична обработка | F7: 741.38 | G7: 4.44828 | H7: 378.87 | I7: 102.26 | J7: =F7+G7+H7 -> 1124.6983 | K7: 872.76587 | L7: =K7+I7 -> 975.02587 | M7: =L7*12 -> 11700.31 | N7: =J7+(19.62%*(J7)+I7) -> 1447.6241 | O7: =N7*12 -> 17371.489 | V7: Автоматизация | W7: 13229.685 | X7: 158756.22 | Y7: 105824.13
A8: 263 | B8: 46023 | D8: =VLOOKUP(C8,'Master Data'!$B$2:$G$155,6,0) -> #N/A | E8: Калкулация | F8: 945.89 | G8: 90.80544 | H8: 561.4 | I8: 102.26 | J8: =F8+G8+H8 -> 1598.0954 | K8: 1240.1221 | L8: =K8+I8 -> 1342.3821 | M8: =L8*12 -> 16108.585 | N8: =J8+(19.62%*(J8)+I8) -> 2013.9018 | O8: =N8*12 -> 24166.821 | V8: Дизайн на автоматизация | W8: 6511.9751 | X8: 78143.701 | Y8: 53116.32
A9: 719 | B9: 46023 | D9: =VLOOKUP(C9,'Master Data'!$B$2:$G$155,6,0) -> #N/A | E9: ТРАНСПОРТ | F9: 741.38 | G9: 17.79312 | H9: 365.57 | I9: 102.26 | J9: =F9+G9+H9 -> 1124.7431 | K9: 872.80066 | L9: =K9+I9 -> 975.06066 | M9: =L9*12 -> 11700.728 | N9: =J9+(19.62%*(J9)+I9) -> 1447.6777 | O9: =N9*12 -> 17372.133 | V9: Дизайн на инструменти | W9: 4644.1087 | X9: 55729.304 | Y9: 37014.89
A10: 67 | B10: 46023 | D10: =VLOOKUP(C10,'Master Data'!$B$2:$G$155,6,0) -> #N/A | E10: Механична обработка | F10: 986.8 | G10: 71.0496 | H10: 277.63 | I10: 102.26 | J10: =F10+G10+H10 -> 1335.4796 | K10: 1036.3322 | L10: =K10+I10 -> 1138.5922 | M10: =L10*12 -> 13663.106 | N10: =J10+(19.62%*(J10)+I10) -> 1699.7607 | O10: =N10*12 -> 20397.128 | V10: Заваръчно | W10: 8010.9454 | X10: 96131.345 | Y10: 64517.725
A11: 615 | B11: 46023 | D11: =VLOOKUP(C11,'Master Data'!$B$2:$G$155,6,0) -> #N/A | E11: Преси | F11: 790.97 | G11: 47.4582 | H11: 269.96 | I11: 102.26 | J11: =F11+G11+H11 -> 1108.3882 | K11: 860.10924 | L11: =K11+I11 -> 962.36924 | M11: =L11*12 -> 11548.431 | N11: =J11+(19.62%*(J11)+I11) -> 1428.114 | O11: =N11*12 -> 17137.368 | V11: Заготовки за производство | W11: 3099.4301 | X11: 37193.161 | Y11: 24990.106
A12: 465 | B12: 46023 | D12: =VLOOKUP(C12,'Master Data'!$B$2:$G$155,6,0) -> #N/A | E12: Инструментален отдел | F12: 940.78 | G12: 152.40636 | H12: 175.5 | I12: 102.26 | J12: =F12+G12+H12 -> 1268.6864 | K12: 984.50062 | L12: =K12+I12 -> 1086.7606 | M12: =L12*12 -> 13041.127 | N12: =J12+(19.62%*(J12)+I12) -> 1619.8626 | O12: =N12*12 -> 19438.351 | V12: Инструментален отдел | W12: 21430.415 | X12: 257164.98 | Y12: 171774.53
A13: 608 | B13: 46023 | D13: =VLOOKUP(C13,'Master Data'!$B$2:$G$155,6,0) -> #N/A | E13: Монтаж | F13: 639.12 | G13: 26.84304 | H13: 71.86 | I13: 102.26 | J13: =F13+G13+H13 -> 737.82304 | K13: 572.55068 | L13: =K13+I13 -> 674.81068 | M13: =L13*12 -> 8097.7281 | N13: =J13+(19.62%*(J13)+I13) -> 984.84392 | O13: =N13*12 -> 11818.127 | V13: Калкулация | W13: 3465.5029 | X13: 41586.035 | Y13: 27839.855
A14: 55 | B14: 46023 | D14: =VLOOKUP(C14,'Master Data'!$B$2:$G$155,6,0) -> #N/A | E14: Преси | F14: 674.91 | G14: 48.59352 | H14: 202.21 | I14: 102.26 | J14: =F14+G14+H14 -> 925.71352 | K14: 718.35369 | L14: =K14+I14 -> 820.61369 | M14: =L14*12 -> 9847.3643 | N14: =J14+(19.62%*(J14)+I14) -> 1209.5985 | O14: =N14*12 -> 14515.182 | V14: Механична обработка | W14: 30821.385 | X14: 369856.62 | Y14: 251728.89
A15: 6 | B15: 46023 | D15: =VLOOKUP(C15,'Master Data'!$B$2:$G$155,6,0) -> #N/A | E15: Монтаж | F15: 639.12 | G15: 76.6944 | H15: 88.25 | I15: 102.26 | J15: =F15+G15+H15 -> 804.0644 | K15: 623.95397 | L15: =K15+I15 -> 726.21397 | M15: =L15*12 -> 8714.5677 | N15: =J15+(19.62%*(J15)+I15) -> 1064.0818 | O15: =N15*12 -> 12768.982 | V15: Монтаж | W15: 48656.153 | X15: 583873.83 | Y15: 397737.9
A16: 697 | B16: 46023 | D16: =VLOOKUP(C16,'Master Data'!$B$2:$G$155,6,0) -> #N/A | E16: Склад | F16: 792.51 | G16: 14.26518 | H16: 323.14 | I16: 102.26 | J16: =F16+G16+H16 -> 1129.9152 | K16: 876.81418 | L16: =K16+I16 -> 979.07418 | M16: =L16*12 -> 11748.89 | N16: =J16+(19.62%*(J16)+I16) -> 1453.8645 | O16: =N16*12 -> 17446.374 | V16: Общи IT | W16: 3965.8929 | X16: 47590.714 | Y16: 31735.216
A17: 736 | B17: 46023 | D17: =VLOOKUP(C17,'Master Data'!$B$2:$G$155,6,0) -> #N/A | E17: Механична обработка | F17: 155.95 | G17: 0 | H17: 0 | I17: 102.26 | J17: =F17+G17+H17 -> 155.95 | K17: 140.35 | L17: =K17+I17 -> 242.61 | M17: =L17*12 -> 2911.32 | N17: =J17+I17 -> 258.21 | O17: =N17*12 -> 3098.52 | V17: Осигуряване на качеството | W17: 8028.3644 | X17: 96340.373 | Y17: 64653.326
A18: 713 | B18: 46023 | D18: =VLOOKUP(C18,'Master Data'!$B$2:$G$155,6,0) -> #N/A | E18: Инструментален отдел | F18: 935.67 | G18: 39.29814 | H18: 282.74 | I18: 102.26 | J18: =F18+G18+H18 -> 1257.7081 | K18: 975.98152 | L18: =K18+I18 -> 1078.2415 | M18: =L18*12 -> 12938.898 | N18: =J18+(19.62%*(J18)+I18) -> 1606.7305 | O18: =N18*12 -> 19280.766 | V18: Поддръжка машини | W18: 3616.1466 | X18: 43393.76 | Y18: 29012.564
A19: 660 | B19: 46023 | D19: =VLOOKUP(C19,'Master Data'!$B$2:$G$155,6,0) -> #N/A | E19: Поддръжка машини | F19: 1135.07 | G19: 115.77714 | H19: 285.3 | I19: 102.26 | J19: =F19+G19+H19 -> 1536.1471 | K19: 1192.0502 | L19: =K19+I19 -> 1294.3102 | M19: =L19*12 -> 15531.722 | N19: =J19+(19.62%*(J19)+I19) -> 1939.7992 | O19: =N19*12 -> 23277.591 | V19: Покупки | W19: 4747.437 | X19: 56969.244 | Y19: 38250.326
A20: 52 | B20: 46023 | D20: =VLOOKUP(C20,'Master Data'!$B$2:$G$155,6,0) -> #N/A | E20: Инструментален отдел | F20: 915.22 | G20: 131.79168 | H20: 1068.6 | I20: 102.26 | J20: =F20+G20+H20 -> 2115.6117 | K20: 1642.16 | L20: =K20+I20 -> 1744.42 | M20: =L20*12 -> 20933.04 | N20: =J20+(19.62%*(J20)+I20) -> 2632.9547 | O20: =N20*12 -> 31595.456 | V20: Преси | W20: 19607.895 | X20: 235294.74 | Y20: 158063.07
A21: 673 | B21: 46023 | D21: =VLOOKUP(C21,'Master Data'!$B$2:$G$155,6,0) -> #N/A | E21: Монтаж | F21: 737 | G21: 8.844 | H21: 242.51 | I21: 102.26 | J21: =F21+G21+H21 -> 988.354 | K21: 766.9627 | L21: =K21+I21 -> 869.2227 | M21: =L21*12 -> 10430.672 | N21: =J21+(19.62%*(J21)+I21) -> 1284.5291 | O21: =N21*12 -> 15414.349 | V21: Производство | W21: 9651.408 | X21: 115816.9 | Y21: 79598.374
A22: 580 | B22: 46023 | D22: =VLOOKUP(C22,'Master Data'!$B$2:$G$155,6,0) -> #N/A | E22: Автоматизация | F22: 1037.93 | G22: 56.04822 | H22: 777.16 | I22: 102.26 | J22: =F22+G22+H22 -> 1871.1382 | K22: 1452.0033 | L22: =K22+I22 -> 1554.2633 | M22: =L22*12 -> 18651.159 | N22: =J22+(19.62%*(J22)+I22) -> 2340.5155 | O22: =N22*12 -> 28086.186 | V22: Развойна дейност | W22: 2432.6107 | X22: 29191.329 | Y22: 19368.088
A23: 682 | B23: 46023 | D23: =VLOOKUP(C23,'Master Data'!$B$2:$G$155,6,0) -> #N/A | E23: Монтаж | F23: 639.12 | G23: 65.19024 | H23: 126.98 | I23: 102.26 | J23: =F23+G23+H23 -> 831.29024 | K23: 645.08123 | L23: =K23+I23 -> 747.34123 | M23: =L23*12 -> 8968.0947 | N23: =J23+(19.62%*(J23)+I23) -> 1096.6494 | O23: =N23*12 -> 13159.793 | V23: Сгради | W23: 3351.8037 | X23: 40221.644 | Y23: 27385.808
A24: 566 | B24: 46023 | D24: =VLOOKUP(C24,'Master Data'!$B$2:$G$155,6,0) -> #N/A | E24: Монтаж | F24: 639.12 | G24: 53.68608 | H24: 58.25 | I24: 102.26 | J24: =F24+G24+H24 -> 751.05608 | K24: 582.81952 | L24: =K24+I24 -> 685.07952 | M24: =L24*12 -> 8220.9542 | N24: =J24+(19.62%*(J24)+I24) -> 1000.6733 | O24: =N24*12 -> 12008.079 | V24: Склад | W24: 5789.9643 | X24: 69479.571 | Y24: 46797.1
A25: 708 | B25: 46023 | D25: =VLOOKUP(C25,'Master Data'!$B$2:$G$155,6,0) -> #N/A | E25: Автоматизация | F25: 1237.33 | G25: 74.2398 | H25: 343.59 | I25: 102.26 | J25: =F25+G25+H25 -> 1655.1598 | K25: 1284.404 | L25: =K25+I25 -> 1386.664 | M25: =L25*12 -> 16639.968 | N25: =J25+(19.62%*(J25)+I25) -> 2082.1622 | O25: =N25*12 -> 24985.946 | V25: Спедиция | W25: 5294.1013 | X25: 63529.215 | Y25: 42505.918
A26: 368 | B26: 46023 | D26: =VLOOKUP(C26,'Master Data'!$B$2:$G$155,6,0) -> #N/A | E26: Механична обработка | F26: 741.38 | G26: 40.03452 | H26: 209.63 | I26: 102.26 | J26: =F26+G26+H26 -> 991.04452 | K26: 769.05055 | L26: =K26+I26 -> 871.31055 | M26: =L26*12 -> 10455.727 | N26: =J26+(19.62%*(J26)+I26) -> 1287.7475 | O26: =N26*12 -> 15452.969 | V26: Счетоводство | W26: 6983.7661 | X26: 83805.193 | Y26: 55658.828
A27: 239 | B27: 46023 | D27: =VLOOKUP(C27,'Master Data'!$B$2:$G$155,6,0) -> #N/A | E27: Заваръчно | F27: 838.52 | G27: 60.37344 | H27: 248.67 | I27: 102.26 | J27: =F27+G27+H27 -> 1147.5634 | K27: 890.50923 | L27: =K27+I27 -> 992.76923 | M27: =L27*12 -> 11913.231 | N27: =J27+(19.62%*(J27)+I27) -> 1474.9754 | O27: =N27*12 -> 17699.705 | V27: ТРАНСПОРТ | W27: 1447.6777 | X27: 17372.133 | Y27: 11700.728
A28: 741 | B28: 46023 | D28: =VLOOKUP(C28,'Master Data'!$B$2:$G$155,6,0) -> #N/A | E28: Монтаж | F28: 690.25 | G28: 0 | H28: 232.64 | I28: 102.26 | J28: =F28+G28+H28 -> 922.89 | K28: 716.16264 | L28: =K28+I28 -> 818.42264 | M28: =L28*12 -> 9821.0717 | N28: =J28+(19.62%*(J28)+I28) -> 1206.221 | O28: =N28*12 -> 14474.652 | V28: Управление на качеството | W28: 3867.5615 | X28: 46410.738 | Y28: 32079.84
A29: 738 | B29: 46023 | D29: =VLOOKUP(C29,'Master Data'!$B$2:$G$155,6,0) -> #N/A | E29: Механична обработка | F29: 792.51 | G29: 57.06072 | H29: 205.03 | I29: 102.26 | J29: =F29+G29+H29 -> 1054.6007 | K29: 818.37016 | L29: =K29+I29 -> 920.63016 | M29: =L29*12 -> 11047.562 | N29: =J29+(19.62%*(J29)+I29) -> 1363.7734 | O29: =N29*12 -> 16365.281 | V29: Управление на проекти | W29: 12211.333 | X29: 146536 | Y29: 101734.56
... A33: 751 | B33: 46023 | D33: =VLOOKUP(C33,'Master Data'!$B$2:$G$155,6,0) -> #N/A | E33: Механична обработка | F33: 987 | G33: 0 | H33: 265.68 | I33: 102.26 | J33: =F33+G33+H33 -> 1252.68 | K33: 972.07968 | L33: =K33+I33 -> 1074.3397 | M33: =L33*12 -> 12892.076 | N33: =J33+(19.62%*(J33)+I33) -> 1600.7158 | O33: =N33*12 -> 19208.59 | V33: Grand Total | W33: 248268.61 | X33: 2979223.4 | Y33: 2012524.5
A34: 623 | B34: 46023 | D34: =VLOOKUP(C34,'Master Data'!$B$2:$G$155,6,0) -> #N/A | E34: Инструментален отдел | F34: 715.81 | G34: 12.88458 | H34: 856.93 | I34: 102.26 | J34: =F34+G34+H34 -> 1585.6246 | K34: 1230.4447 | L34: =K34+I34 -> 1332.7047 | M34: =L34*12 -> 15992.456 | N34: =J34+(19.62%*(J34)+I34) -> 1998.9841 | O34: =N34*12 -> 23987.809
A35: 745 | B35: 46023 | D35: =VLOOKUP(C35,'Master Data'!$B$2:$G$155,6,0) -> #N/A | E35: Механична обработка | F35: 1083.94 | G35: 32.5182 | H35: 333.36 | I35: 102.26 | J35: =F35+G35+H35 -> 1449.8182 | K35: 1125.0589 | L35: =K35+I35 -> 1227.3189 | M35: =L35*12 -> 14727.827 | N35: =J35+(19.62%*(J35)+I35) -> 1836.5325 | O35: =N35*12 -> 22038.39
A36: 756 | B36: 46023 | D36: =VLOOKUP(C36,'Master Data'!$B$2:$G$155,6,0) -> #N/A | E36: Монтаж | F36: 640 | G36: 0 | H36: 85.53 | I36: 102.26 | J36: =F36+G36+H36 -> 725.53 | K36: 563.01128 | L36: =K36+I36 -> 665.27128 | M36: =L36*12 -> 7983.2554 | N36: =J36+(19.62%*(J36)+I36) -> 970.13899 | O36: =N36*12 -> 11641.668 | V36: Years (Effective Date) | W36: 2026
A37: 404 | B37: 46023 | D37: =VLOOKUP(C37,'Master Data'!$B$2:$G$155,6,0) -> #N/A | E37: Монтаж | F37: 639.12 | G37: 30.67776 | H37: 88.25 | I37: 102.26 | J37: =F37+G37+H37 -> 758.04776 | K37: 588.24506 | L37: =K37+I37 -> 690.50506 | M37: =L37*12 -> 8286.0607 | N37: =J37+(19.62%*(J37)+I37) -> 1009.0367 | O37: =N37*12 -> 12108.441 | V37: Quarters (Effective Date) | W37: (All)
A38: 277 | B38: 46023 | D38: =VLOOKUP(C38,'Master Data'!$B$2:$G$155,6,0) -> #N/A | E38: Преси | F38: 664.68 | G38: 43.86888 | H38: 887.6 | I38: 102.26 | J38: =F38+G38+H38 -> 1596.1489 | K38: 1238.6115 | L38: =K38+I38 -> 1340.8715 | M38: =L38*12 -> 16090.458 | N38: =J38+(19.62%*(J38)+I38) -> 2011.5733 | O38: =N38*12 -> 24138.879 | V38: Months (Effective Date) | W38: (All)
A39: 644 | B39: 46023 | D39: =VLOOKUP(C39,'Master Data'!$B$2:$G$155,6,0) -> #N/A | E39: Осигуряване на качеството | F39: 971.46 | G39: 69.94512 | H39: 0 | I39: 102.26 | J39: =F39+G39+H39 -> 1041.4051 | K39: 808.13037 | L39: =K39+I39 -> 910.39037 | M39: =L39*12 -> 10924.684 | N39: =J39+(19.62%*(J39)+I39) -> 1347.9888 | O39: =N39*12 -> 16175.866 | V39: Effective Date | W39: (All)
A40: 472 | B40: 46023 | D40: =VLOOKUP(C40,'Master Data'!$B$2:$G$155,6,0) -> #N/A | E40: Инструментален отдел | F40: 715.81 | G40: 42.9486 | H40: 414.15 | I40: 102.26 | J40: =F40+G40+H40 -> 1172.9086 | K40: 910.17707 | L40: =K40+I40 -> 1012.4371 | M40: =L40*12 -> 12149.245 | N40: =J40+(19.62%*(J40)+I40) -> 1505.2933 | O40: =N40*12 -> 18063.519
A41: 542 | B41: 46023 | D41: =VLOOKUP(C41,'Master Data'!$B$2:$G$155,6,0) -> #N/A | E41: Механична обработка | F41: 790.97 | G41: 23.7291 | H41: 381.42 | I41: 102.26 | J41: =F41+G41+H41 -> 1196.1191 | K41: 928.18842 | L41: =K41+I41 -> 1030.4484 | M41: =L41*12 -> 12365.381 | N41: =J41+(19.62%*(J41)+I41) -> 1533.0577 | O41: =N41*12 -> 18396.692 | V41: Row Labels | W41: Sum of Month Employer Cost | X41: Sum of Annual Employer Cost | Y41: Sum of Annual Salary (netto)
A42: 494 | B42: 46023 | D42: =VLOOKUP(C42,'Master Data'!$B$2:$G$155,6,0) -> #N/A | E42: Осигуряване на качеството | F42: 792.51 | G42: 42.79554 | H42: 499.53 | I42: 102.26 | J42: =F42+G42+H42 -> 1334.8355 | K42: 1035.8324 | L42: =K42+I42 -> 1138.0924 | M42: =L42*12 -> 13657.109 | N42: =J42+(19.62%*(J42)+I42) -> 1698.9903 | O42: =N42*12 -> 20387.883 | V42: 1000 | W42: 9651.408 | X42: 115816.9 | Y42: 79598.374
A43: 677 | B43: 46023 | D43: =VLOOKUP(C43,'Master Data'!$B$2:$G$155,6,0) -> #N/A | E43: Шприцоване | F43: 639.12 | G43: 80.52912 | H43: 280.19 | I43: 102.26 | J43: =F43+G43+H43 -> 999.83912 | K43: 775.87516 | L43: =K43+I43 -> 878.13516 | M43: =L43*12 -> 10537.622 | N43: =J43+(19.62%*(J43)+I43) -> 1298.2676 | O43: =N43*12 -> 15579.211 | V43: 1100 | W43: 3099.4301 | X43: 37193.161 | Y43: 24990.106
A44: 665 | B44: 46023 | D44: =VLOOKUP(C44,'Master Data'!$B$2:$G$155,6,0) -> #N/A | E44: Монтаж | F44: 1027.7 | G44: 12.3324 | H44: 332.34 | I44: 102.26 | J44: =F44+G44+H44 -> 1372.3724 | K44: 1064.961 | L44: =K44+I44 -> 1167.221 | M44: =L44*12 -> 14006.652 | N44: =J44+(19.62%*(J44)+I44) -> 1743.8919 | O44: =N44*12 -> 20926.702 | V44: 1200 | W44: 18238.479 | X44: 218861.75 | Y44: 146971.58
A45: 704 | B45: 46023 | D45: =VLOOKUP(C45,'Master Data'!$B$2:$G$155,6,0) -> #N/A | E45: Механична обработка | F45: 792.51 | G45: 4.75506 | H45: 393.18 | I45: 102.26 | J45: =F45+G45+H45 -> 1190.4451 | K45: 923.78537 | L45: =K45+I45 -> 1026.0454 | M45: =L45*12 -> 12312.544 | N45: =J45+(19.62%*(J45)+I45) -> 1526.2704 | O45: =N45*12 -> 18315.245 | V45: 1300 | W45: 30821.385 | X45: 369856.62 | Y45: 251728.89
A46: 703 | B46: 46023 | D46: =VLOOKUP(C46,'Master Data'!$B$2:$G$155,6,0) -> #N/A | E46: Управление на качеството | F46: 2326.38 | G46: 251.24904 | H46: 570.09 | I46: 102.26 | J46: =F46+G46+H46 -> 3147.719 | K46: 2571.06 | L46: =K46+I46 -> 2673.32 | M46: =L46*12 -> 32079.84 | N46: =J46+(19.62%*(J46)+I46) -> 3867.5615 | O46: =N46*12 -> 46410.738 | V46: 1400 | W46: 9380.361 | X46: 112564.33 | Y46: 75609.21
A47: 650 | B47: 46023 | D47: =VLOOKUP(C47,'Master Data'!$B$2:$G$155,6,0) -> #N/A | E47: Преси | F47: 674.91 | G47: 12.14838 | H47: 609.95 | I47: 102.26 | J47: =F47+G47+H47 -> 1297.0084 | K47: 1006.4785 | L47: =K47+I47 -> 1108.7385 | M47: =L47*12 -> 13304.862 | N47: =J47+(19.62%*(J47)+I47) -> 1653.7414 | O47: =N47*12 -> 19844.897 | V47: 1600 | W47: 46912.261 | X47: 562947.13 | Y47: 383731.24
A48: 46 | B48: 46023 | D48: =VLOOKUP(C48,'Master Data'!$B$2:$G$155,6,0) -> #N/A | E48: Поддръжка машини | F48: 641.17 | G48: 107.71656 | H48: 567.02 | I48: 102.26 | J48: =F48+G48+H48 -> 1315.9066 | K48: 1021.1435 | L48: =K48+I48 -> 1123.4035 | M48: =L48*12 -> 13480.842 | N48: =J48+(19.62%*(J48)+I48) -> 1676.3474 | O48: =N48*12 -> 20116.169 | V48: 1680 | W48: 1743.8919 | X48: 20926.702 | Y48: 14006.652
A49: 327 | B49: 46023 | D49: =VLOOKUP(C49,'Master Data'!$B$2:$G$155,6,0) -> #N/A | E49: Инструментален отдел | F49: 715.81 | G49: 42.9486 | H49: 1048.15 | I49: 102.26 | J49: =F49+G49+H49 -> 1806.9086 | K49: 1402.1611 | L49: =K49+I49 -> 1504.4211 | M49: =L49*12 -> 18053.053 | N49: =J49+(19.62%*(J49)+I49) -> 2263.6841 | O49: =N49*12 -> 27164.209 | V49: 1800 | W49: 9134.7021 | X49: 109616.43 | Y49: 73345.947
A50: 742 | B50: 46023 | D50: =VLOOKUP(C50,'Master Data'!$B$2:$G$155,6,0) -> #N/A | E50: Управление ЧР | F50: 1175.98 | G50: 35.2794 | H50: 370.18 | I50: 102.26 | J50: =F50+G50+H50 -> 1581.4394 | K50: 1227.197 | L50: =K50+I50 -> 1329.457 | M50: =L50*12 -> 15953.484 | N50: =J50+(19.62%*(J50)+I50) -> 1993.9778 | O50: =N50*12 -> 23927.734 | V50: 2100 | W50: 21430.415 | X50: 257164.98 | Y50: 171774.53
A51: 737 | B51: 46023 | D51: =VLOOKUP(C51,'Master Data'!$B$2:$G$155,6,0) -> #N/A | E51: Механична обработка | F51: 155.95 | G51: 0 | H51: 0 | I51: 102.26 | J51: =F51+G51+H51 -> 155.95 | K51: 140.35 | L51: =K51+I51 -> 242.61 | M51: =L51*12 -> 2911.32 | N51: =J51+I51 -> 258.21 | O51: =N51*12 -> 3098.52 | V51: 2220 | W51: 13229.685 | X51: 158756.22 | Y51: 105824.13
A52: 275 | B52: 46023 | D52: =VLOOKUP(C52,'Master Data'!$B$2:$G$155,6,0) -> #N/A | E52: Монтаж | F52: 639.12 | G52: 42.18192 | H52: 88.25 | I52: 102.26 | J52: =F52+G52+H52 -> 769.55192 | K52: 597.17229 | L52: =K52+I52 -> 699.43229 | M52: =L52*12 -> 8393.1875 | N52: =J52+(19.62%*(J52)+I52) -> 1022.798 | O52: =N52*12 -> 12273.576 | V52: 2410 | W52: 4644.1087 | X52: 55729.304 | Y52: 37014.89
A53: 393 | B53: 46023 | D53: =VLOOKUP(C53,'Master Data'!$B$2:$G$155,6,0) -> #N/A | E53: Инструментален отдел | F53: 915.22 | G53: 49.42188 | H53: 584.92 | I53: 102.26 | J53: =F53+G53+H53 -> 1549.5619 | K53: 1202.46 | L53: =K53+I53 -> 1304.72 | M53: =L53*12 -> 15656.64 | N53: =J53+(19.62%*(J53)+I53) -> 1955.8459 | O53: =N53*12 -> 23470.151 | V53: 2440 | W53: 6511.9751 | X53: 78143.701 | Y53: 53116.32
A54: 711 | B54: 46023 | D54: =VLOOKUP(C54,'Master Data'!$B$2:$G$155,6,0) -> #N/A | E54: Управление на проекти | F54: 2965.5 | G54: 177.93 | H54: 1238.35 | I54: 102.26 | J54: =F54+G54+H54 -> 4381.78 | K54: 3681.71 | L54: =K54+I54 -> 3783.97 | M54: =L54*12 -> 45407.64 | N54: =J54+(19.62%*(J54)+I54) -> 5343.7452 | O54: =N54*12 -> 64124.943 | V54: 3110 | W54: 4747.437 | X54: 56969.244 | Y54: 38250.326
A55: 282 | B55: 46023 | D55: =VLOOKUP(C55,'Master Data'!$B$2:$G$155,6,0) -> #N/A | E55: Механична обработка | F55: 986.8 | G55: 65.1288 | H55: 605.37 | I55: 102.26 | J55: =F55+G55+H55 -> 1657.2988 | K55: 1286.0639 | L55: =K55+I55 -> 1388.3239 | M55: =L55*12 -> 16659.886 | N55: =J55+(19.62%*(J55)+I55) -> 2084.7208 | O55: =N55*12 -> 25016.65 | V55: 3200 | W55: 5789.9643 | X55: 69479.571 | Y55: 46797.1
A56: 692 | B56: 46023 | D56: =VLOOKUP(C56,'Master Data'!$B$2:$G$155,6,0) -> #N/A | E56: Автоматизация | F56: 1523.65 | G56: 82.2771 | H56: 423.86 | I56: 102.26 | J56: =F56+G56+H56 -> 2029.7871 | K56: 1575.1148 | L56: =K56+I56 -> 1677.3748 | M56: =L56*12 -> 20128.497 | N56: =J56+(19.62%*(J56)+I56) -> 2530.2913 | O56: =N56*12 -> 30363.496 | V56: 3500 | W56: 8028.3644 | X56: 96340.373 | Y56: 64653.326
A57: 172 | B57: 46023 | D57: =VLOOKUP(C57,'Master Data'!$B$2:$G$155,6,0) -> #N/A | E57: Производство | F57: 2096.3 | G57: 176.0892 | H57: 478.57 | I57: 102.26 | J57: =F57+G57+H57 -> 2750.9592 | K57: 2213.97 | L57: =K57+I57 -> 2316.23 | M57: =L57*12 -> 27794.76 | N57: =J57+(19.62%*(J57)+I57) -> 3392.9574 | O57: =N57*12 -> 40715.489 | V57: 3900 | W57: 1447.6777 | X57: 17372.133 | Y57: 11700.728
A58: 658 | B58: 46023 | D58: =VLOOKUP(C58,'Master Data'!$B$2:$G$155,6,0) -> #N/A | E58: Спедиция | F58: 1227.11 | G58: 51.53862 | H58: 522.54 | I58: 102.26 | J58: =F58+G58+H58 -> 1801.1886 | K58: 1397.7224 | L58: =K58+I58 -> 1499.9824 | M58: =L58*12 -> 17999.788 | N58: =J58+(19.62%*(J58)+I58) -> 2256.8418 | O58: =N58*12 -> 27082.102 | V58: 4100 | W58: 1843.2646 | X58: 22119.175 | Y58: 14780.234
A59: 228 | B59: 46023 | D59: =VLOOKUP(C59,'Master Data'!$B$2:$G$155,6,0) -> #N/A | E59: Заготовки за производство | F59: 674.91 | G59: 48.59352 | H59: 453.17 | I59: 102.26 | J59: =F59+G59+H59 -> 1176.6735 | K59: 913.09865 | L59: =K59+I59 -> 1015.3587 | M59: =L59*12 -> 12184.304 | N59: =J59+(19.62%*(J59)+I59) -> 1509.7969 | O59: =N59*12 -> 18117.562 | V59: 4300 | W59: 5294.1013 | X59: 63529.215 | Y59: 42505.918
A60: 669 | B60: 46023 | D60: =VLOOKUP(C60,'Master Data'!$B$2:$G$155,6,0) -> #N/A | E60: Механична обработка | F60: 790.97 | G60: 9.49164 | H60: 263.83 | I60: 102.26 | J60: =F60+G60+H60 -> 1064.2916 | K60: 825.89031 | L60: =K60+I60 -> 928.15031 | M60: =L60*12 -> 11137.804 | N60: =J60+(19.62%*(J60)+I60) -> 1375.3657 | O60: =N60*12 -> 16504.388 | V60: 4400 | W60: 3465.5029 | X60: 41586.035 | Y60: 27839.855
A61: 633 | B61: 46023 | D61: =VLOOKUP(C61,'Master Data'!$B$2:$G$155,6,0) -> #N/A | E61: Производство | F61: 2224.12 | G61: 106.75776 | H61: 1274.14 | I61: 102.26 | J61: =F61+G61+H61 -> 3605.0178 | K61: 2982.63 | L61: =K61+I61 -> 3084.89 | M61: =L61*12 -> 37018.68 | N61: =J61+(19.62%*(J61)+I61) -> 4414.5822 | O61: =N61*12 -> 52974.987 | V61: 4500 | W61: 2432.6107 | X61: 29191.329 | Y61: 19368.088
A62: 244 | B62: 46023 | D62: =VLOOKUP(C62,'Master Data'!$B$2:$G$155,6,0) -> #N/A | E62: Сгради | F62: 741.38 | G62: 22.2414 | H62: 245.42 | I62: 102.26 | J62: =F62+G62+H62 -> 1009.0414 | K62: 783.01613 | L62: =K62+I62 -> 885.27613 | M62: =L62*12 -> 10623.314 | N62: =J62+(19.62%*(J62)+I62) -> 1309.2753 | O62: =N62*12 -> 15711.304 | V62: 4600 | W62: 12211.333 | X62: 146536 | Y62: 101734.56
A63: 632 | B63: 46023 | D63: =VLOOKUP(C63,'Master Data'!$B$2:$G$155,6,0) -> #N/A | E63: Монтаж | F63: 639.12 | G63: 42.18192 | H63: 57.57 | I63: 102.26 | J63: =F63+G63+H63 -> 738.87192 | K63: 573.36461 | L63: =K63+I63 -> 675.62461 | M63: =L63*12 -> 8107.4953 | N63: =J63+(19.62%*(J63)+I63) -> 986.09859 | O63: =N63*12 -> 11833.183 | V63: 5400 | W63: 6983.7661 | X63: 83805.193 | Y63: 55658.828
... A68: 754 | B68: 46023 | D68: =VLOOKUP(C68,'Master Data'!$B$2:$G$155,6,0) -> #N/A | E68: Монтаж | F68: 640 | G68: 0 | H68: 85.53 | I68: 102.26 | J68: =F68+G68+H68 -> 725.53 | K68: 563.01128 | L68: =K68+I68 -> 665.27128 | M68: =L68*12 -> 7983.2554 | N68: =J68+(19.62%*(J68)+I68) -> 970.13899 | O68: =N68*12 -> 11641.668 | V68: 6410 | W68: 3616.1466 | X68: 43393.76 | Y68: 29012.564
A69: 490 | B69: 46023 | D69: =VLOOKUP(C69,'Master Data'!$B$2:$G$155,6,0) -> #N/A | E69: Монтаж | F69: 639.12 | G69: 23.00832 | H69: 184.5 | I69: 102.26 | J69: =F69+G69+H69 -> 846.62832 | K69: 656.98358 | L69: =K69+I69 -> 759.24358 | M69: =L69*12 -> 9110.9229 | N69: =J69+(19.62%*(J69)+I69) -> 1114.9968 | O69: =N69*12 -> 13379.962 | V69: Grand Total | W69: 248268.61 | X69: 2979223.4 | Y69: 2012524.5
A70: 670 | B70: 45748 | D70: =VLOOKUP(C70,'Master Data'!$B$2:$G$155,6,0) -> #N/A | E70: Управление ЧР | F70: 1135.07 | G70: 108.96672 | H70: 542.01 | I70: 102.26 | J70: =F70+G70+H70 -> 1786.0467 | K70: 1385.9723 | L70: =K70+I70 -> 1488.2323 | M70: =L70*12 -> 17858.787 | N70: =J70+(19.62%*(J70)+I70) -> 2238.7291 | O70: =N70*12 -> 26864.749
A71: 670 | B71: 46023 | D71: =VLOOKUP(C71,'Master Data'!$B$2:$G$155,6,0) -> #N/A | E71: Управление ЧР | F71: 1135.07 | G71: 108.96672 | H71: 806.15 | I71: 102.26 | J71: =F71+G71+H71 -> 2050.1867 | K71: 1590.9449 | L71: =K71+I71 -> 1693.2049 | M71: =L71*12 -> 20318.459 | N71: =J71+(19.62%*(J71)+I71) -> 2554.6934 | O71: =N71*12 -> 30656.32 | P71: =(J71-J70)/J70 -> 0.14789087 | Q71: нови задължения | R71: Мария Венева | S71: 46010 | T71: изготвяне на заплати
A72: 133 | B72: 46023 | D72: =VLOOKUP(C72,'Master Data'!$B$2:$G$155,6,0) -> #N/A | E72: Инструментален отдел | F72: 915.22 | G72: 131.79168 | H72: 548.62 | I72: 102.26 | J72: =F72+G72+H72 -> 1595.6317 | K72: 1238.2102 | L72: =K72+I72 -> 1340.4702 | M72: =L72*12 -> 16085.642 | N72: =J72+(19.62%*(J72)+I72) -> 2010.9546 | O72: =N72*12 -> 24131.455
A73: 396 | B73: 46023 | D73: =VLOOKUP(C73,'Master Data'!$B$2:$G$155,6,0) -> #N/A | E73: Инструментален отдел | F73: 715.81 | G73: 60.12804 | H73: 409.03 | I73: 102.26 | J73: =F73+G73+H73 -> 1184.968 | K73: 919.5352 | L73: =K73+I73 -> 1021.7952 | M73: =L73*12 -> 12261.542 | N73: =J73+(19.62%*(J73)+I73) -> 1519.7188 | O73: =N73*12 -> 18236.625
A74: 537 | B74: 46023 | D74: =VLOOKUP(C74,'Master Data'!$B$2:$G$155,6,0) -> #N/A | E74: Преси | F74: 664.68 | G74: 23.92848 | H74: 839.03 | I74: 102.26 | J74: =F74+G74+H74 -> 1527.6385 | K74: 1185.4475 | L74: =K74+I74 -> 1287.7075 | M74: =L74*12 -> 15452.49 | N74: =J74+(19.62%*(J74)+I74) -> 1929.6211 | O74: =N74*12 -> 23155.454
A75: 506 | B75: 46023 | D75: =VLOOKUP(C75,'Master Data'!$B$2:$G$155,6,0) -> #N/A | E75: Заваръчно | F75: 838.52 | G75: 45.28008 | H75: 195.73 | I75: 102.26 | J75: =F75+G75+H75 -> 1079.5301 | K75: 837.71534 | L75: =K75+I75 -> 939.97534 | M75: =L75*12 -> 11279.704 | N75: =J75+(19.62%*(J75)+I75) -> 1393.5939 | O75: =N75*12 -> 16723.127
A76: 587 | B76: 46023 | D76: =VLOOKUP(C76,'Master Data'!$B$2:$G$155,6,0) -> #N/A | E76: Монтаж | F76: 639.12 | G76: 15.33888 | H76: 184.5 | I76: 102.26 | J76: =F76+G76+H76 -> 838.95888 | K76: 651.03209 | L76: =K76+I76 -> 753.29209 | M76: =L76*12 -> 9039.5051 | N76: =J76+(19.62%*(J76)+I76) -> 1105.8226 | O76: =N76*12 -> 13269.871
A77: 688 | B77: 46023 | D77: =VLOOKUP(C77,'Master Data'!$B$2:$G$155,6,0) -> #N/A | E77: Монтаж | F77: 641.68 | G77: 7.70016 | H77: 313.42 | I77: 102.26 | J77: =F77+G77+H77 -> 962.80016 | K77: 747.13292 | L77: =K77+I77 -> 849.39292 | M77: =L77*12 -> 10192.715 | N77: =J77+(19.62%*(J77)+I77) -> 1253.9616 | O77: =N77*12 -> 15047.539
A78: 637 | B78: 46023 | D78: =VLOOKUP(C78,'Master Data'!$B$2:$G$155,6,0) -> #N/A | E78: Покупки | F78: 715.81 | G78: 55.83318 | H78: 0 | I78: 102.26 | J78: =F78+G78+H78 -> 771.64318 | K78: 598.79511 | L78: =K78+I78 -> 701.05511 | M78: =L78*12 -> 8412.6613 | N78: =J78+(19.62%*(J78)+I78) -> 1025.2996 | O78: =N78*12 -> 12303.595
A79: 712 | B79: 46023 | D79: =VLOOKUP(C79,'Master Data'!$B$2:$G$155,6,0) -> #N/A | E79: Дизайн на инструменти | F79: 1380.49 | G79: 8.28294 | H79: 460.15 | I79: 102.26 | J79: =F79+G79+H79 -> 1848.9229 | K79: 1434.7642 | L79: =K79+I79 -> 1537.0242 | M79: =L79*12 -> 18444.29 | N79: =J79+(19.62%*(J79)+I79) -> 2313.9416 | O79: =N79*12 -> 27767.299
A80: 749 | B80: 46023 | D80: =VLOOKUP(C80,'Master Data'!$B$2:$G$155,6,0) -> #N/A | E80: Автоматизация | F80: 1710.01 | G80: 61.56036 | H80: 508 | I80: 102.26 | J80: =F80+G80+H80 -> 2279.5704 | K80: 1789.72 | L80: =K80+I80 -> 1891.98 | M80: =L80*12 -> 22703.76 | N80: =J80+(19.62%*(J80)+I80) -> 2829.0821 | O80: =N80*12 -> 33948.985
A81: 466 | B81: 46023 | D81: =VLOOKUP(C81,'Master Data'!$B$2:$G$155,6,0) -> #N/A | E81: Шприцоване | F81: 639.12 | G81: 26.84304 | H81: 233.34 | I81: 102.26 | J81: =F81+G81+H81 -> 899.30304 | K81: 697.85916 | L81: =K81+I81 -> 800.11916 | M81: =L81*12 -> 9601.4299 | N81: =J81+(19.62%*(J81)+I81) -> 1178.0063 | O81: =N81*12 -> 14136.076
A82: 734 | B82: 46023 | D82: =VLOOKUP(C82,'Master Data'!$B$2:$G$155,6,0) -> #N/A | E82: Механична обработка | F82: 155.95 | G82: 0 | H82: 0 | I82: 102.26 | J82: =F82+G82+H82 -> 155.95 | K82: 140.35 | L82: =K82+I82 -> 242.61 | M82: =L82*12 -> 2911.32 | N82: =J82+I82 -> 258.21 | O82: =N82*12 -> 3098.52
A83: 264 | B83: 46023 | D83: =VLOOKUP(C83,'Master Data'!$B$2:$G$155,6,0) -> #N/A | E83: Осигуряване на качеството | F83: 792.51 | G83: 80.83602 | H83: 392.67 | I83: 102.26 | J83: =F83+G83+H83 -> 1266.016 | K83: 982.42843 | L83: =K83+I83 -> 1084.6884 | M83: =L83*12 -> 13016.261 | N83: =J83+(19.62%*(J83)+I83) -> 1616.6684 | O83: =N83*12 -> 19400.02
A84: 728 | B84: 46023 | D84: =VLOOKUP(C84,'Master Data'!$B$2:$G$155,6,0) -> #N/A | E84: Осигуряване на качеството | F84: 879.43 | G84: 26.3829 | H84: 272.52 | I84: 102.26 | J84: =F84+G84+H84 -> 1178.3329 | K84: 914.38633 | L84: =K84+I84 -> 1016.6463 | M84: =L84*12 -> 12199.756 | N84: =J84+(19.62%*(J84)+I84) -> 1511.7818 | O84: =N84*12 -> 18141.382
A85: 686 | B85: 46023 | D85: =VLOOKUP(C85,'Master Data'!$B$2:$G$155,6,0) -> #N/A | E85: Калкулация | F85: 690.25 | G85: 8.283 | H85: 429.49 | I85: 102.26 | J85: =F85+G85+H85 -> 1128.023 | K85: 875.34585 | L85: =K85+I85 -> 977.60585 | M85: =L85*12 -> 11731.27 | N85: =J85+(19.62%*(J85)+I85) -> 1451.6011 | O85: =N85*12 -> 17419.213
A86: 746 | B86: 46023 | D86: =VLOOKUP(C86,'Master Data'!$B$2:$G$155,6,0) -> #N/A | E86: Счетоводство | F86: 1124.85 | G86: 53.9928 | H86: 337.45 | I86: 102.26 | J86: =F86+G86+H86 -> 1516.2928 | K86: 1176.6432 | L86: =K86+I86 -> 1278.9032 | M86: =L86*12 -> 15346.839 | N86: =J86+(19.62%*(J86)+I86) -> 1916.0494 | O86: =N86*12 -> 22992.593
A87: 740 | B87: 46023 | D87: =VLOOKUP(C87,'Master Data'!$B$2:$G$155,6,0) -> #N/A | E87: Монтаж | F87: 639.12 | G87: 0 | H87: 88.25 | I87: 102.26 | J87: =F87+G87+H87 -> 727.37 | K87: 564.43912 | L87: =K87+I87 -> 666.69912 | M87: =L87*12 -> 8000.3894 | N87: =J87+(19.62%*(J87)+I87) -> 972.33999 | O87: =N87*12 -> 11668.08
A88: 696 | B88: 46023 | D88: =VLOOKUP(C88,'Master Data'!$B$2:$G$155,6,0) -> #N/A | E88: Продажби | F88: 989.35 | G88: 5.9361 | H88: 460.16 | I88: 102.26 | J88: =F88+G88+H88 -> 1455.4461 | K88: 1129.4262 | L88: =K88+I88 -> 1231.6862 | M88: =L88*12 -> 14780.234 | N88: =J88+(19.62%*(J88)+I88) -> 1843.2646 | O88: =N88*12 -> 22119.175
A89: 731 | B89: 46023 | D89: =VLOOKUP(C89,'Master Data'!$B$2:$G$155,6,0) -> #N/A | E89: Монтаж | F89: 639.12 | G89: 0 | H89: 88.25 | I89: 102.26 | J89: =F89+G89+H89 -> 727.37 | K89: 564.43912 | L89: =K89+I89 -> 666.69912 | M89: =L89*12 -> 8000.3894 | N89: =J89+(19.62%*(J89)+I89) -> 972.33999 | O89: =N89*12 -> 11668.08
A90: 485 | B90: 46023 | D90: =VLOOKUP(C90,'Master Data'!$B$2:$G$155,6,0) -> #N/A | E90: Монтаж | F90: 639.12 | G90: 38.3472 | H90: 169.15 | I90: 102.26 | J90: =F90+G90+H90 -> 846.6172 | K90: 656.97495 | L90: =K90+I90 -> 759.23495 | M90: =L90*12 -> 9110.8194 | N90: =J90+(19.62%*(J90)+I90) -> 1114.9835 | O90: =N90*12 -> 13379.802
A91: 3 | B91: 46023 | D91: =VLOOKUP(C91,'Master Data'!$B$2:$G$155,6,0) -> #N/A | E91: Механична обработка | F91: 741.38 | G91: 53.37936 | H91: 204.52 | I91: 102.26 | J91: =F91+G91+H91 -> 999.27936 | K91: 775.44078 | L91: =K91+I91 -> 877.70078 | M91: =L91*12 -> 10532.409 | N91: =J91+(19.62%*(J91)+I91) -> 1297.598 | O91: =N91*12 -> 15571.176
A92: 705 | B92: 46023 | D92: =VLOOKUP(C92,'Master Data'!$B$2:$G$155,6,0) -> #N/A | E92: Сгради | F92: 639.12 | G92: 3.83472 | H92: 0 | I92: 102.26 | J92: =F92+G92+H92 -> 642.95472 | K92: 498.93286 | L92: =K92+I92 -> 601.19286 | M92: =L92*12 -> 7214.3144 | N92: =J92+(19.62%*(J92)+I92) -> 871.36244 | O92: =N92*12 -> 10456.349
A93: 40 | B93: 46023 | D93: =VLOOKUP(C93,'Master Data'!$B$2:$G$155,6,0) -> #N/A | E93: Покупки | F93: 986.8 | G93: 213.1488 | H93: 153.39 | I93: 102.26 | J93: =F93+G93+H93 -> 1353.3388 | K93: 1050.1909 | L93: =K93+I93 -> 1152.4509 | M93: =L93*12 -> 13829.411 | N93: =J93+(19.62%*(J93)+I93) -> 1721.1239 | O93: =N93*12 -> 20653.486
A94: 655 | B94: 46023 | D94: =VLOOKUP(C94,'Master Data'!$B$2:$G$155,6,0) -> #N/A | E94: Управление ЧР | F94: 1431.62 | G94: 51.53832 | H94: 0 | I94: 102.26 | J94: =F94+G94+H94 -> 1483.1583 | K94: 1150.9309 | L94: =K94+I94 -> 1253.1909 | M94: =L94*12 -> 15038.29 | N94: =J94+(19.62%*(J94)+I94) -> 1876.414 | O94: =N94*12 -> 22516.968
... A118: 338 | B118: 46023 | D118: =VLOOKUP(C118,'Master Data'!$B$2:$G$155,6,0) -> #N/A | E118: Монтаж | F118: 639.12 | G118: 38.3472 | H118: 88.25 | I118: 102.26 | J118: =F118+G118+H118 -> 765.7172 | K118: 594.19655 | L118: =K118+I118 -> 696.45655 | M118: =L118*12 -> 8357.4786 | N118: =J118+(19.62%*(J118)+I118) -> 1018.2109 | O118: =N118*12 -> 12218.531
A119: 735 | B119: 46023 | D119: =VLOOKUP(C119,'Master Data'!$B$2:$G$155,6,0) -> #N/A | E119: Механична обработка | F119: 155.95 | G119: 0 | H119: 0 | I119: 102.26 | J119: =F119+G119+H119 -> 155.95 | K119: 140.35 | L119: =K119+I119 -> 242.61 | M119: =L119*12 -> 2911.32 | N119: =J119+I119 -> 258.21 | O119: =N119*12 -> 3098.52
A120: 315 | B120: 46023 | D120: =VLOOKUP(C120,'Master Data'!$B$2:$G$155,6,0) -> #N/A | E120: Монтаж | F120: 737 | G120: 44.22 | H120: 273.5 | I120: 102.26 | J120: =F120+G120+H120 -> 1054.72 | K120: 818.46272 | L120: =K120+I120 -> 920.72272 | M120: =L120*12 -> 11048.673 | N120: =J120+(19.62%*(J120)+I120) -> 1363.9161 | O120: =N120*12 -> 16366.993
A121: 616 | B121: 46023 | D121: =VLOOKUP(C121,'Master Data'!$B$2:$G$155,6,0) -> #N/A | E121: Монтаж | F121: 639.12 | G121: 26.84304 | H121: 0 | I121: 102.26 | J121: =F121+G121+H121 -> 665.96304 | K121: 516.78732 | L121: =K121+I121 -> 619.04732 | M121: =L121*12 -> 7428.5678 | N121: =J121+(19.62%*(J121)+I121) -> 898.88499 | O121: =N121*12 -> 10786.62
A122: 680 | B122: 46023 | D122: =VLOOKUP(C122,'Master Data'!$B$2:$G$155,6,0) -> #N/A | E122: Монтаж | F122: 639.12 | G122: 26.84304 | H122: 69.08 | I122: 102.26 | J122: =F122+G122+H122 -> 735.04304 | K122: 570.3934 | L122: =K122+I122 -> 672.6534 | M122: =L122*12 -> 8071.8408 | N122: =J122+(19.62%*(J122)+I122) -> 981.51848 | O122: =N122*12 -> 11778.222
A123: 250 | B123: 46023 | D123: =VLOOKUP(C123,'Master Data'!$B$2:$G$155,6,0) -> #N/A | E123: Склад | F123: 690.25 | G123: 45.5565 | H123: 530.72 | I123: 102.26 | J123: =F123+G123+H123 -> 1266.5265 | K123: 982.82456 | L123: =K123+I123 -> 1085.0846 | M123: =L123*12 -> 13021.015 | N123: =J123+(19.62%*(J123)+I123) -> 1617.279 | O123: =N123*12 -> 19407.348
A124: 11 | B124: 46023 | D124: =VLOOKUP(C124,'Master Data'!$B$2:$G$155,6,0) -> #N/A | E124: Механична обработка | F124: 741.38 | G124: 177.9312 | H124: 80.4 | I124: 102.26 | J124: =F124+G124+H124 -> 999.7112 | K124: 775.77589 | L124: =K124+I124 -> 878.03589 | M124: =L124*12 -> 10536.431 | N124: =J124+(19.62%*(J124)+I124) -> 1298.1145 | O124: =N124*12 -> 15577.374
A125: 698 | B125: 46023 | D125: =VLOOKUP(C125,'Master Data'!$B$2:$G$155,6,0) -> #N/A | E125: Управление на проекти | F125: 1845.77 | G125: 11.07462 | H125: 621.73 | I125: 102.26 | J125: =F125+G125+H125 -> 2478.5746 | K125: 1968.82 | L125: =K125+I125 -> 2071.08 | M125: =L125*12 -> 24852.96 | N125: =J125+(19.62%*(J125)+I125) -> 3067.131 | O125: =N125*12 -> 36805.572
A126: 83 | B126: 46023 | D126: =VLOOKUP(C126,'Master Data'!$B$2:$G$155,6,0) -> #N/A | E126: Преси | F126: 986.8 | G126: 112.4952 | H126: 252.33 | I126: 102.26 | J126: =F126+G126+H126 -> 1351.6252 | K126: 1048.8612 | L126: =K126+I126 -> 1151.1212 | M126: =L126*12 -> 13813.454 | N126: =J126+(19.62%*(J126)+I126) -> 1719.0741 | O126: =N126*12 -> 20628.889
A127: 325 | B127: 46023 | D127: =VLOOKUP(C127,'Master Data'!$B$2:$G$155,6,0) -> #N/A | E127: Дизайн на автоматизация | F127: 623.78 | G127: 37.4268 | H127: 1910.7 | I127: 102.26 | J127: =F127+G127+H127 -> 2571.9068 | K127: 2052.83 | L127: =K127+I127 -> 2155.09 | M127: =L127*12 -> 25861.08 | N127: =J127+(19.62%*(J127)+I127) -> 3178.7749 | O127: =N127*12 -> 38145.299
A128: 706 | B128: 46023 | D128: =VLOOKUP(C128,'Master Data'!$B$2:$G$155,6,0) -> #N/A | E128: Монтаж | F128: 639.12 | G128: 3.83472 | H128: 88.25 | I128: 102.26 | J128: =F128+G128+H128 -> 731.20472 | K128: 567.41486 | L128: =K128+I128 -> 669.67486 | M128: =L128*12 -> 8036.0984 | N128: =J128+(19.62%*(J128)+I128) -> 976.92709 | O128: =N128*12 -> 11723.125
A129: 685 | B129: 46023 | D129: =VLOOKUP(C129,'Master Data'!$B$2:$G$155,6,0) -> #N/A | E129: Монтаж | F129: 736.27 | G129: 66.2643 | H129: 260.76 | I129: 102.26 | J129: =F129+G129+H129 -> 1063.2943 | K129: 825.11638 | L129: =K129+I129 -> 927.37638 | M129: =L129*12 -> 11128.517 | N129: =J129+(19.62%*(J129)+I129) -> 1374.1726 | O129: =N129*12 -> 16490.072
A130: 755 | B130: 46023 | D130: =VLOOKUP(C130,'Master Data'!$B$2:$G$155,6,0) -> #N/A | E130: Склад | F130: 750 | G130: 0 | H130: 255.18 | I130: 102.26 | J130: =F130+G130+H130 -> 1005.18 | K130: 780.01968 | L130: =K130+I130 -> 882.27968 | M130: =L130*12 -> 10587.356 | N130: =J130+(19.62%*(J130)+I130) -> 1304.6563 | O130: =N130*12 -> 15655.876
...

Sheet Monthly Budget Control
A1: Month | B1: Department | C1: Cost Center | D1: Approved Annual Budget (netto) | E1: Approved Monthly Budget (netto) | F1: Actual Payroll (netto) | G1: Variance | H1: Variance %
A2: 2 | B2: Автоматизация | C2: 2200 | D2: 105824.13 | E2: =D2/12 -> 8818.6778 | F2: 8517.6 | G2: =F2-E2 -> -301.07783 | H2: =(F2-E2)/E2 -> -0.034140926
A3: 2 | B3: Дизайн на автоматизация | C3: 2400 | D3: 53116.32 | E3: =D3/12 -> 4426.36 | F3: 4426.36 | G3: =F3-E3 -> 0 | H3: =(F3-E3)/E3 -> 0
A4: 2 | B4: Дизайн на инструменти | C4: 2410 | D4: 37014.89 | E4: =D4/12 -> 3084.5742 | F4: 2939.06 | G4: =F4-E4 -> -145.51419 | H4: =(F4-E4)/E4 -> -0.047174807
A5: 2 | B5: Заваръчно | C5: 1400 | D5: 64517.725 | E5: =D5/12 -> 5376.4771 | F5: 5783.46 | G5: =F5-E5 -> 406.98288 | H5: =(F5-E5)/E5 -> 0.075696943
A6: 2 | B6: Заготовки за производство | C6: 1100 | D6: 24990.106 | E6: =D6/12 -> 2082.5088 | F6: 2096.89 | G6: =F6-E6 -> 14.3812 | H6: =(F6-E6)/E6 -> 0.006905709
A7: 2 | B7: Инструментален отдел | C7: 2100 | D7: 171774.53 | E7: =D7/12 -> 14314.544 | F7: 14328.72 | G7: =F7-E7 -> 14.176235 | H7: =(F7-E7)/E7 -> 0.00099033787
A8: 2 | B8: Калкулация | C8: 4400 | D8: 27839.855 | E8: =D8/12 -> 2319.9879 | F8: 2301.57 | G8: =F8-E8 -> -18.417909 | H8: =(F8-E8)/E8 -> -0.0079387954
A9: 2 | B9: Механична обработка | C9: 1300 | D9: 251728.89 | E9: =D9/12 -> 20977.407 | F9: 20344.11 | G9: =F9-E9 -> -633.29733 | H9: =(F9-E9)/E9 -> -0.030189495
A10: 2 | B10: Монтаж | C10: 1600 | D10: 397737.9 | E10: =D10/12 -> 33144.825 | F10: 36614.5 | G10: =F10-E10 -> 3469.6753 | H10: =(F10-E10)/E10 -> 0.10468226
A11: 2 | B11: Общи IT | C11: 5600 | D11: 31735.216 | E11: =D11/12 -> 2644.6014 | F11: 2629.77 | G11: =F11-E11 -> -14.831374 | H11: =(F11-E11)/E11 -> -0.0056081699
A12: 2 | B12: Осигуряване на качеството | C12: 3500 | D12: 64653.326 | E12: =D12/12 -> 5387.7772 | F12: 4579.54 | G12: =F12-E12 -> -808.23717 | H12: =(F12-E12)/E12 -> -0.1500131
A13: 2 | B13: Поддръжка машини | C13: 6410 | D13: 29012.564 | E13: =D13/12 -> 2417.7137 | F13: 2417.66 | G13: =F13-E13 -> -0.0536712 | H13: =(F13-E13)/E13 -> -2.2199155e-05
... A27: 2 | B27: Продажби | C27: 4100 | D27: 14780.234 | E27: =D27/12 -> 1231.6862 | F27: 1231.66 | G27: =F27-E27 -> -0.0261736 | H27: =(F27-E27)/E27 -> -2.1250218e-05

Sheet Monthly Release
A1: Month | B1: Department | C1: Cost Center | D1: Total Payroll | E1: Budget | F1: Variance | G1: Variance % | H1: Release Status (Yes/No) | I1: Released By | J1: Release Date
A2: 2 | B2: Автоматизация | C2: 2200 | D2: 8517.6 | E2: 8818.6778 | F2: =D2-E2 -> -301.07783 | G2: =(D2-E2)/E2 -> -0.034140926
A3: 2 | B3: Дизайн на автоматизация | C3: 2400 | D3: 4426.36 | E3: 4426.36 | F3: =D3-E3 -> 0 | G3: =(D3-E3)/E3 -> 0
A4: 2 | B4: Дизайн на инструменти | C4: 2410 | D4: 2939.06 | E4: 3084.5742 | F4: =D4-E4 -> -145.51419 | G4: =(D4-E4)/E4 -> -0.047174807
A5: 2 | B5: Заваръчно | C5: 1400 | D5: 5783.46 | E5: 5376.4771 | F5: =D5-E5 -> 406.98288 | G5: =(D5-E5)/E5 -> 0.075696943
A6: 2 | B6: Заготовки за производство | C6: 1100 | D6: 2096.89 | E6: 2082.5088 | F6: =D6-E6 -> 14.3812 | G6: =(D6-E6)/E6 -> 0.006905709
A7: 2 | B7: Инструментален отдел | C7: 2100 | D7: 14328.72 | E7: 14314.544 | F7: =D7-E7 -> 14.176235 | G7: =(D7-E7)/E7 -> 0.00099033787
A8: 2 | B8: Калкулация | C8: 4400 | D8: 2301.57 | E8: 2319.9879 | F8: =D8-E8 -> -18.417909 | G8: =(D8-E8)/E8 -> -0.0079387954
A9: 2 | B9: Механична обработка | C9: 1300 | D9: 20344.11 | E9: 20977.407 | F9: =D9-E9 -> -633.29733 | G9: =(D9-E9)/E9 -> -0.030189495
A10: 2 | B10: Монтаж | C10: 1600 | D10: 36614.5 | E10: 33144.825 | F10: =D10-E10 -> 3469.6753 | G10: =(D10-E10)/E10 -> 0.10468226
A11: 2 | B11: Общи IT | C11: 5600 | D11: 2629.77 | E11: 2644.6014 | F11: =D11-E11 -> -14.831374 | G11: =(D11-E11)/E11 -> -0.0056081699
A12: 2 | B12: Осигуряване на качеството | C12: 3500 | D12: 4579.54 | E12: 5387.7772 | F12: =D12-E12 -> -808.23717 | G12: =(D12-E12)/E12 -> -0.1500131
A13: 2 | B13: Поддръжка машини | C13: 6410 | D13: 2417.66 | E13: 2417.7137 | F13: =D13-E13 -> -0.0536712 | G13: =(D13-E13)/E13 -> -2.2199155e-05
... A27: 2 | B27: Продажби | C27: 4100 | D27: 1231.66 | E27: 1231.6862 | F27: =D27-E27 -> -0.0261736 | G27: =(D27-E27)/E27 -> -2.1250218e-05

Sheet Cost Center Structure
A1: Level | B1: Code | C1: Cost Center Name | D1: Level 1 Group | E1: Level 2 Group | F1: Level 3 Group | G1: Notes
A2: 0 | B2: 99999 | C2: 99999
A3: 1 | B3: 1 | C3: General areas - production | D3: General areas - production
A4: 2 | B4: 10 | C4: Manufacturing | D4: General areas - production | E4: Manufacturing
A5: 3 | B5: 100 | C5: Manufacturing | D5: General areas - production | E5: Manufacturing | F5: Manufacturing
A6: 2 | B6: 11 | C6: Setup & Deburr | D6: General areas - production | E6: Setup & Deburr
A7: 3 | B7: 110 | C7: Setup & Deburring | D7: General areas - production | E7: Setup & Deburr | F7: Setup & Deburring
A8: 3 | B8: 111 | C8: Cutting | D8: General areas - production | E8: Setup & Deburr | F8: Cutting
A9: 3 | B9: 112 | C9: Brushing | D9: General areas - production | E9: Setup & Deburr | F9: Brushing
A10: 3 | B10: 113 | C10: Belt grinding | D10: General areas - production | E10: Setup & Deburr | F10: Belt grinding
A11: 3 | B11: 114 | C11: Sand blasting | D11: General areas - production | E11: Setup & Deburr | F11: Sand blasting
A12: 3 | B12: 115 | C12: Vibro grinding | D12: General areas - production | E12: Setup & Deburr | F12: Vibro grinding
A13: 3 | B13: 119 | C13: Deburring | D13: General areas - production | E13: Setup & Deburr | F13: Deburring
A14: 2 | B14: 12 | C14: Presses | D14: General areas - production | E14: Presses
A15: 3 | B15: 120 | C15: Presses | D15: General areas - production | E15: Presses | F15: Presses
A16: 3 | B16: 121 | C16: Automatic presses | D16: General areas - production | E16: Presses | F16: Automatic presses
A17: 3 | B17: 122 | C17: Hydraulic presses | D17: General areas - production | E17: Presses | F17: Hydraulic presses
A18: 3 | B18: 123 | C18: Excenter presses | D18: General areas - production | E18: Presses | F18: Excenter presses
A19: 3 | B19: 124 | C19: Production island brushes | D19: General areas - production | E19: Presses | F19: Production island brushes
A20: 3 | B20: 125 | C20: Drilling | D20: General areas - production | E20: Presses | F20: Drilling
A21: 3 | B21: 126 | C21: Miscellaneous press-department | D21: General areas - production | E21: Presses | F21: Miscellaneous press-department
A22: 3 | B22: 127 | C22: Press brake | D22: General areas - production | E22: Presses | F22: Press brake
A23: 2 | B23: 13 | C23: Mechanic | D23: General areas - production | E23: Mechanic
A24: 3 | B24: 130 | C24: Mechanic | D24: General areas - production | E24: Mechanic | F24: Mechanic
A25: 3 | B25: 131 | C25: Cam lathe | D25: General areas - production | E25: Mechanic | F25: Cam lathe
A26: 3 | B26: 132 | C26: NC turning | D26: General areas - production | E26: Mechanic | F26: NC turning
A27: 3 | B27: 133 | C27: Turning | D27: General areas - production | E27: Mechanic | F27: Turning
A28: 3 | B28: 134 | C28: NC milling | D28: General areas - production | E28: Mechanic | F28: NC milling
A29: 3 | B29: 139 | C29: Miscellaneous mechanic | D29: General areas - production | E29: Mechanic | F29: Miscellaneous mechanic
A30: 2 | B30: 14 | C30: Welding | D30: General areas - production | E30: Welding
A31: 3 | B31: 140 | C31: Welding | D31: General areas - production | E31: Welding | F31: Welding
A32: 3 | B32: 142 | C32: Welding robots | D32: General areas - production | E32: Welding | F32: Welding robots
A33: 3 | B33: 148 | C33: Miscellaneous welding | D33: General areas - production | E33: Welding | F33: Miscellaneous welding
A34: 2 | B34: 16 | C34: Assembly | D34: General areas - production | E34: Assembly
A35: 3 | B35: 160 | C35: Assembly | D35: General areas - production | E35: Assembly | F35: Assembly
A36: 3 | B36: 161 | C36: Riveting machines | D36: General areas - production | E36: Assembly | F36: Riveting machines
A37: 3 | B37: 167 | C37: Special equipment assembly | D37: General areas - production | E37: Assembly | F37: Special equipment assembly
A38: 3 | B38: 168 | C38: Special equipment assembly | D38: General areas - production | E38: Assembly | F38: Special equipment assembly
A39: 3 | B39: 169 | C39: Manual workplaces assembly | D39: General areas - production | E39: Assembly | F39: Manual workplaces assembly
A40: 2 | B40: 18 | C40: Injection Molding | D40: General areas - production | E40: Injection Molding
A41: 3 | B41: 180 | C41: Injection Molding | D41: General areas - production | E41: Injection Molding | F41: Injection Molding
A42: 3 | B42: 182 | C42: Injectionpresses > 100T | D42: General areas - production | E42: Injection Molding | F42: Injectionpresses > 100T
A43: 3 | B43: 183 | C43: Injectionpresse > 50T < 100T | D43: General areas - production | E43: Injection Molding | F43: Injectionpresse > 50T < 100T
A44: 3 | B44: 184 | C44: Injectionpresse < 50T | D44: General areas - production | E44: Injection Molding | F44: Injectionpresse < 50T
A45: 3 | B45: 189 | C45: Manual workplaces molding | D45: General areas - production | E45: Injection Molding | F45: Manual workplaces molding
A46: 1 | B46: 2 | C46: Manufacturing sub branches | D46: Manufacturing sub branches
A47: 2 | B47: 20 | C47: Tooling | D47: Manufacturing sub branches | E47: Tooling
A48: 3 | B48: 200 | C48: Tooling | D48: Manufacturing sub branches | E48: Tooling | F48: Tooling
A49: 2 | B49: 21 | C49: Tooling | D49: Manufacturing sub branches | E49: Tooling
A50: 3 | B50: 210 | C50: Tooling | D50: Manufacturing sub branches | E50: Tooling | F50: Tooling
A51: 3 | B51: 211 | C51: Miscellaneous machines OR | D51: Manufacturing sub branches | E51: Tooling | F51: Miscellaneous machines OR
A52: 3 | B52: 214 | C52: Milling OR | D52: Manufacturing sub branches | E52: Tooling | F52: Milling OR
A53: 3 | B53: 216 | C53: EDM | D53: Manufacturing sub branches | E53: Tooling | F53: EDM
A54: 3 | B54: 217 | C54: Grinding OR | D54: Manufacturing sub branches | E54: Tooling | F54: Grinding OR
A55: 3 | B55: 219 | C55: Assembly tooling | D55: Manufacturing sub branches | E55: Tooling | F55: Assembly tooling
A56: 2 | B56: 22 | C56: Automation | D56: Manufacturing sub branches | E56: Automation
A57: 3 | B57: 220 | C57: Automation | D57: Manufacturing sub branches | E57: Automation | F57: Automation
A58: 3 | B58: 222 | C58: Automation | D58: Manufacturing sub branches | E58: Automation | F58: Automation
A59: 2 | B59: 24 | C59: Engineering | D59: Manufacturing sub branches | E59: Engineering
A60: 3 | B60: 240 | C60: Engineering | D60: Manufacturing sub branches | E60: Engineering | F60: Engineering
A61: 3 | B61: 241 | C61: Tooling design | D61: Manufacturing sub branches | E61: Engineering | F61: Tooling design
A62: 3 | B62: 242 | C62: Lean engineering | D62: Manufacturing sub branches | E62: Engineering | F62: Lean engineering
A63: 3 | B63: 243 | C63: Job engineering | D63: Manufacturing sub branches | E63: Engineering | F63: Job engineering
A64: 3 | B64: 244 | C64: Automation design | D64: Manufacturing sub branches | E64: Engineering | F64: Automation design
A65: 2 | B65: 25 | C65: Quality assurance (DO NOT USE) | D65: Manufacturing sub branches | E65: Quality assurance (DO NOT USE)
A66: 3 | B66: 250 | C66: DO NOT USE Quality assurance | D66: Manufacturing sub branches | E66: Quality assurance (DO NOT USE) | F66: DO NOT USE Quality assurance
A67: 3 | B67: 251 | C67: DO NOT USE Quality control | D67: Manufacturing sub branches | E67: Quality assurance (DO NOT USE) | F67: DO NOT USE Quality control
A68: 3 | B68: 252 | C68: DO NOT USE Calibration | D68: Manufacturing sub branches | E68: Quality assurance (DO NOT USE) | F68: DO NOT USE Calibration
A69: 2 | B69: 29 | C69: External Works | D69: Manufacturing sub branches | E69: External Works
A70: 3 | B70: 296 | C70: External Works | D70: Manufacturing sub branches | E70: External Works | F70: External Works
A71: 1 | B71: 3 | C71: Materials | D71: Materials
A72: 2 | B72: 30 | C72: Materials management | D72: Materials | E72: Materials management
A73: 3 | B73: 300 | C73: Materials management | D73: Materials | E73: Materials management | F73: Materials management
A74: 2 | B74: 31 | C74: Purchasing | D74: Materials | E74: Purchasing
A75: 3 | B75: 310 | C75: Purchasing | D75: Materials | E75: Purchasing | F75: Purchasing
A76: 3 | B76: 311 | C76: Purchasing department | D76: Materials | E76: Purchasing | F76: Purchasing department
A77: 3 | B77: 312 | C77: Laboratory | D77: Materials | E77: Purchasing | F77: Laboratory
A78: 2 | B78: 32 | C78: Warehouse | D78: Materials | E78: Warehouse
A79: 3 | B79: 320 | C79: Warehouse | D79: Materials | E79: Warehouse | F79: Warehouse
A80: 3 | B80: 321 | C80: Stock | D80: Materials | E80: Warehouse | F80: Stock
A81: 3 | B81: 322 | C81: Goods reception | D81: Materials | E81: Warehouse | F81: Goods reception
A82: 3 | B82: 323 | C82: Warehouse accounting | D82: Materials | E82: Warehouse | F82: Warehouse accounting
A83: 2 | B83: 35 | C83: Quality assurance | D83: Materials | E83: Quality assurance
A84: 3 | B84: 350 | C84: Quality assurance | D84: Materials | E84: Quality assurance | F84: Quality assurance
A85: 3 | B85: 351 | C85: Quality control | D85: Materials | E85: Quality assurance | F85: Quality control
A86: 3 | B86: 352 | C86: Calibration | D86: Materials | E86: Quality assurance | F86: Calibration
A87: 2 | B87: 39 | C87: Fleet | D87: Materials | E87: Fleet
A88: 3 | B88: 390 | C88: Fleet | D88: Materials | E88: Fleet | F88: Fleet
A89: 3 | B89: 391 | C89: TIR | D89: Materials | E89: Fleet | F89: TIR
A90: 3 | B90: 392 | C90: Trucks | D90: Materials | E90: Fleet | F90: Trucks
A91: 3 | B91: 393 | C91: Cars | D91: Materials | E91: Fleet | F91: Cars
A92: 3 | B92: 394 | C92: Forklift | D92: Materials | E92: Fleet | F92: Forklift
A93: 3 | B93: 395 | C93: Stacker | D93: Materials | E93: Fleet | F93: Stacker
A94: 1 | B94: 4 | C94: Distribution | D94: Distribution
A95: 2 | B95: 40 | C95: Distribution | D95: Distribution | E95: Distribution
A96: 3 | B96: 400 | C96: Distribution | D96: Distribution | E96: Distribution | F96: Distribution
A97: 2 | B97: 41 | C97: Sales | D97: Distribution | E97: Sales
A98: 3 | B98: 410 | C98: Sales | D98: Distribution | E98: Sales | F98: Sales
A99: 2 | B99: 42 | C99: Marketing | D99: Distribution | E99: Marketing
A100: 3 | B100: 420 | C100: Marketing | D100: Distribution | E100: Marketing | F100: Marketing
...
